{
    "id": "b9f2739d-f43c-4911-a018-1e396c9b91ce",
    "type": "run",
    "app_id": "com.nike.sport.running.ios",
    "start_epoch_ms": 1509235338561,
    "end_epoch_ms": 1509235338561,
    "last_modified": 1510961413759,
    "active_duration_ms": 0,
    "session": false,
    "delete_indicator": false,
    "summaries": [],
    "sources": [],
    "tags": {
        "com_nike_running_goaltype": "freeRun",
        "location": "outdoors"
    },
    "change_tokens": [
        "b62e22955ad64de7cef6a3de8655495c20a4f20742b2f52f45997cca5a2a1058:1510961413759"
    ],
    "metric_types": [],
    "moments": []
}